hackingtools/__init__.py
hackingtools/core/Blockchain.py
hackingtools/core/Config.py
hackingtools/core/Connections.py
hackingtools/core/DjangoFunctions.py
hackingtools/core/Exceptions.py
hackingtools/core/Logger.py
hackingtools/core/Objects.py
hackingtools/core/Pool.py
hackingtools/core/Repositories.py
hackingtools/core/TelegramBot.py
hackingtools/core/Utils.py
hackingtools/core/UtilsDjangoViewsAuto.py
hackingtools/core/__init__.py
hackingtools/core/config.json
hackingtools/core/config_django.json
hackingtools/core/apis_files/a48WqyDpLxS22gsm0kMzWAOLbDVr6x0B.htpass
hackingtools/core/config_modules_django/av_evasion/ht_crypter.json
hackingtools/core/config_modules_django/connector/ht_openvas.json
hackingtools/core/config_modules_django/connector/ht_qualys.json
hackingtools/core/config_modules_django/connector/ht_sia.json
hackingtools/core/config_modules_django/connector/ht_ssh.json
hackingtools/core/config_modules_django/crackers/ht_bruteforce.json
hackingtools/core/config_modules_django/crackers/ht_router.json
hackingtools/core/config_modules_django/crackers/ht_unzip.json
hackingtools/core/config_modules_django/crypto/ht_hash.json
hackingtools/core/config_modules_django/crypto/ht_rc4.json
hackingtools/core/config_modules_django/crypto/ht_rsa.json
hackingtools/core/config_modules_django/files/ht_parser.json
hackingtools/core/config_modules_django/forensic/ht_metadata.json
hackingtools/core/config_modules_django/forensic/ht_virustotal.json
hackingtools/core/config_modules_django/malware/ht_keylogger.json
hackingtools/core/config_modules_django/malware/ht_rat.json
hackingtools/core/config_modules_django/network/ht_scapy.json
hackingtools/core/config_modules_django/osint/ht_facebook.json
hackingtools/core/config_modules_django/osint/ht_finder.json
hackingtools/core/config_modules_django/osint/ht_instagram.json
hackingtools/core/config_modules_django/osint/ht_nmap.json
hackingtools/core/config_modules_django/osint/ht_pastebin.json
hackingtools-3.2.3.dist-info/LICENSE.md
hackingtools-3.2.3.dist-info/METADATA
hackingtools-3.2.3.dist-info/WHEEL
hackingtools-3.2.3.dist-info/top_level.txt
hackingtools-3.2.3.dist-info/RECORD
